eng_dic/__init__.py
eng_dic/main.py
eng_dic-0.1.dist-info/METADATA
eng_dic-0.1.dist-info/WHEEL
eng_dic-0.1.dist-info/entry_points.txt
eng_dic-0.1.dist-info/top_level.txt
eng_dic-0.1.dist-info/RECORD
