Metadata-Version: 2.1
Name: eng-dic
Version: 0.1
Requires-Dist: requests >=1.1.1
